greetuser/__init__.py
greetuser/main.py
rishabh_greetuser-0.0.11.dist-info/METADATA
rishabh_greetuser-0.0.11.dist-info/WHEEL
rishabh_greetuser-0.0.11.dist-info/top_level.txt
rishabh_greetuser-0.0.11.dist-info/RECORD
