Metadata-Version: 2.4
Name: rishabh-greetuser
Version: 0.0.11
Summary: A simple package to greet a user
Author-email: Rishabh <rishabhraj777@gmail.com>
License-Expression: MIT
Requires-Python: >=3.7
